LICENSE
MANIFEST.in
README.rst
run_test_and_report.sh
setup.py
tests.py
vimmock/__init__.py
vimmock/mocked.py
vimmock/tests.py
vimmock.egg-info/PKG-INFO
vimmock.egg-info/SOURCES.txt
vimmock.egg-info/dependency_links.txt
vimmock.egg-info/not-zip-safe
vimmock.egg-info/top_level.txt