Metadata-Version: 1.1
Name: vimmock
Version: 0.1.0
Summary: vim mock object for easier testing of vim plugins written in Python.
Home-page: http://github.com/lukaszb/vimmock
Author: Lukasz Balcerzak
Author-email: lukaszbalcerzak@gmail.com
License: BSD
Download-URL: http://github.com/lukaszb/vimmock/downloads
Platform: UNKNOWN
Classifier: Development Status :: 4 - Beta
Classifier: Environment :: Plugins
Classifier: Intended Audience :: Developers
Classifier: License :: OSI Approved :: BSD License
Classifier: Operating System :: OS Independent
Classifier: Programming Language :: Python
Classifier: Topic :: Software Development :: Testing
Classifier: Topic :: Text Editors
